orivec/__init__.py
orivec/__main__.py
orivec/cli.py
orivec/core.py
orivec/ref_gen.py
orivec-0.1.1.dist-info/licenses/LICENSE
orivec-0.1.1.dist-info/METADATA
orivec-0.1.1.dist-info/WHEEL
orivec-0.1.1.dist-info/entry_points.txt
orivec-0.1.1.dist-info/top_level.txt
orivec-0.1.1.dist-info/RECORD
