Metadata-Version: 2.4
Name: OriVec
Version: 0.1.1
Summary: Compute orientation order parameters in polycrystals with point cloud ICP method.
Author-email: theNotfish <taoyuze.lv@outlook.com>
License: Proprietary
Classifier: Programming Language :: Python :: 3
Classifier: Programming Language :: Python :: 3 :: Only
Classifier: License :: Other/Proprietary License
Classifier: Operating System :: OS Independent
Requires-Python: >=3.10
License-File: LICENSE
Requires-Dist: numpy
Requires-Dist: ase
Requires-Dist: open3d
Requires-Dist: spglib
Provides-Extra: develop
Requires-Dist: pytest; extra == "develop"
Requires-Dist: typer; extra == "develop"
Dynamic: license-file
